Workbook

Sheet Instructions
A1: MS Excel Practical Exam
A2: Total Questions: 30
A3: Difficulty Level: Medium
A4: Syllabus: Formulas, Logical Functions, Lookups, INDEX-MATCH, Pivot Tables & Charts, Data Analysis
A5: Attempt all questions using appropriate Excel tools/functions.

Sheet Sales_Data
A1: Order_ID | B1: Region | C1: Salesperson | D1: Product | E1: Quantity | F1: Unit_Price | G1: Sales_Date
A2: 301 | B2: North | C2: Amit | D2: Laptop | E2: 2 | F2: 45000 | G2: 05-01-2025
A3: 302 | B3: South | C3: Riya | D3: Mobile | E3: 5 | F3: 15000 | G3: 07-01-2025
A4: 303 | B4: East | C4: Kunal | D4: Tablet | E4: 3 | F4: 18000 | G4: 10-01-2025
A5: 304 | B5: West | C5: Neha | D5: Laptop | E5: 1 | F5: 45000 | G5: 12-01-2025
A6: 305 | B6: North | C6: Amit | D6: Mobile | E6: 4 | F6: 15000 | G6: 15-01-2025
A7: 306 | B7: South | C7: Riya | D7: Laptop | E7: 2 | F7: 45000 | G7: 18-01-2025

Sheet Product_Master
A1: Product | B1: Category | C1: GST_%
A2: Laptop | B2: Electronics | C2: 18
A3: Mobile | B3: Electronics | C3: 12
A4: Tablet | B4: Electronics | C4: 12

Sheet Student_Marks
A1: Student_ID | B1: Name | C1: Maths | D1: Statistics | E1: Excel | F1: Attendance_%
A2: 1 | B2: Rahul | C2: 78 | D2: 82 | E2: 85 | F2: 92
A3: 2 | B3: Sneha | C3: 88 | D3: 91 | E3: 90 | F3: 96
A4: 3 | B4: Arjun | C4: 65 | D4: 70 | E4: 72 | F4: 85
A5: 4 | B5: Pooja | C5: 92 | D5: 89 | E5: 94 | F5: 98
A6: 5 | B6: Vikas | C6: 55 | D6: 60 | E6: 58 | F6: 80

Sheet Questions
A1: 1. Calculate Total Sales for each order (Quantity × Unit_Price). | J1: 2
A2: 2. Calculate GST Amount using VLOOKUP from Product_Master. | J2: 2
A3: 3. Find Final Amount payable (Total Sales + GST). | J3: 2
A4: 4. Find Grand Total of Final Amount. | J4: 2
A5: 5. Count total number of orders using COUNTA. | J5: 2
A6: 6. Find Region-wise total sales using SUMIF. | J6: 2
A7: 7. Use IF to classify Quantity as High (>3) or Low (<=3). | J7: 2
A8: 8. Find the maximum and minimum Final Amount. | J8: 2
A9: 9. Extract month name from Sales_Date. | J9: 2
A10: 10. Sort Sales_Data by Final Amount (Descending). | J10: 2
A11: 11. Use INDEX-MATCH to fetch Product Category. | J11: 2
A12: 12. Calculate average marks of each student. | J12: 2
... A30: 30. Protect the Student_Marks sheet. | J30: 2
J32: =SUM(J1:J30) -> 60

Sheet Answers
A1: Order_ID | B1: Region | C1: Salesperson | D1: Product | E1: Quantity | F1: Unit_Price | G1: Sales_Date | J1: Product | K1: Category | L1: GST_% | O1: Student_ID | P1: Name | Q1: Maths | R1: Statistics | S1: Excel | T1: Attendance_%
A2: 301 | B2: North | C2: Amit | D2: Laptop | E2: 2 | F2: 45000 | G2: 45662 | J2: Laptop | K2: Electronics | L2: 18 | O2: 1 | P2: Rahul | Q2: 78 | R2: 82 | S2: 85 | T2: 92
A3: 302 | B3: South | C3: Riya | D3: Mobile | E3: 5 | F3: 15000 | G3: 07-01-2025 | J3: Mobile | K3: Electronics | L3: 12 | O3: 2 | P3: Sneha | Q3: 88 | R3: 91 | S3: 90 | T3: 96
A4: 303 | B4: East | C4: Kunal | D4: Tablet | E4: 3 | F4: 18000 | G4: 10-01-2025 | J4: Tablet | K4: Electronics | L4: 12 | O4: 3 | P4: Arjun | Q4: 65 | R4: 70 | S4: 72 | T4: 85
A5: 304 | B5: West | C5: Neha | D5: Laptop | E5: 1 | F5: 45000 | G5: 12-01-2025 | O5: 4 | P5: Pooja | Q5: 92 | R5: 89 | S5: 94 | T5: 98
A6: 305 | B6: North | C6: Amit | D6: Mobile | E6: 4 | F6: 15000 | G6: 15-01-2025 | O6: 5 | P6: Vikas | Q6: 55 | R6: 60 | S6: 58 | T6: 80
A7: 306 | B7: South | C7: Riya | D7: Laptop | E7: 2 | F7: 45000 | G7: 18-01-2025
A12: Q1 | B12: Total Amount | D12: Q2 | E12: GST Amount | G12: Q3 | H12: Final Amount | J12: Q4 | K12: Grand Total of Final Amount | O12: Q5 | P12: Count Total Order | T12: Q6 | U12: Region | V12: Sales
B13: =F2*E2 -> 90000 | E13: =B13*VLOOKUP(D2,$J$1:$L$4,3,0)% -> 16200 | H13: 106200 | K13: =SUM(H13:H18) -> 477180 | P13: =COUNT(E2:E7) -> 6 | U13: North | V13: =SUMIF(B2:B7,B2,B13:B18) -> 150000
B14: =F3*E3 -> 75000 | E14: =B14*VLOOKUP(D3,$J$1:$L$4,3,0)% -> 9000 | H14: 84000 | U14: South | V14: =SUMIF(B3:B8,B3,B14:B19) -> 165000
B15: =F4*E4 -> 54000 | E15: =B15*VLOOKUP(D4,$J$1:$L$4,3,0)% -> 6480 | H15: 60480 | U15: East | V15: =SUMIF(B4:B9,B4,B15:B20) -> 54000
B16: =F5*E5 -> 45000 | E16: =B16*VLOOKUP(D5,$J$1:$L$4,3,0)% -> 8100 | H16: 53100 | U16: West | V16: =SUMIF(B5:B10,B5,B16:B21) -> 45000
B17: =F6*E6 -> 60000 | E17: =B17*VLOOKUP(D6,$J$1:$L$4,3,0)% -> 7200 | H17: 67200
B18: =F7*E7 -> 90000 | E18: =B18*VLOOKUP(D7,$J$1:$L$4,3,0)% -> 16200 | H18: 106200
A21: Q7 | B21: Quantity | D21: Q8 | E21: Maximum | F21: =MAX(Answers!H13:H18) -> 106200 | H21: Q9 | I21: Sale Month | K21: Q10 | L21: Sales-Date | M21: Final Amount | O21: Q12 | P21: Average Marks | S21: Q13 | T21: Topper | U21: Average Marks
B22: =IF(E2>3,"High","Low") -> Low | E22: Minimum | F22: =MIN(H13:H18) -> 53100 | I22: =TEXT(G2,"mmmm") -> January | L22: {=_xlfn.SORTBY(G2:G7,H13:H18,-1)} -> 45662 | M22: {=_xlfn._xlws.SORT(H13:H18,1,-1)} -> 106200 | P22: =AVERAGE(Q2:S2) -> 81.666667 | T22: =_xlfn.XLOOKUP(U22,P22:P26,P2:P6) -> Pooja | U22: =MAX(P22:P26) -> 91.666667
B23: =IF(E3>3,"High","Low") -> High | I23: =TEXT(G3,"mmmm") -> January | L23: 18-01-2025 | M23: 106200 | P23: =AVERAGE(Q3:S3) -> 89.666667
B24: =IF(E4>3,"High","Low") -> Low | I24: =TEXT(G4,"mmmm") -> January | L24: 07-01-2025 | M24: 84000 | P24: =AVERAGE(Q4:S4) -> 69
B25: =IF(E5>3,"High","Low") -> Low | I25: =TEXT(G5,"mmmm") -> January | L25: 15-01-2025 | M25: 67200 | P25: =AVERAGE(Q5:S5) -> 91.666667
B26: =IF(E6>3,"High","Low") -> High | I26: =TEXT(G6,"mmmm") -> January | L26: 10-01-2025 | M26: 60480 | P26: =AVERAGE(Q6:S6) -> 57.666667
B27: =IF(E7>3,"High","Low") -> Low | I27: =TEXT(G7,"mmmm") -> January | L27: 12-01-2025 | M27: 53100
A30: Q14 | B30: Above 90% attendance | E30: Q15 | F30: Eligible Students | H30: Q20 | I30: Median Of Statics Marks | L30: Q21 | M30: SD of Excel Marks | O30: Q22 | P30: Concated Name | S30: Q23 | T30: first 2 letters of Salesperson
B31: =COUNTIF(T2:T6,">90") -> 3 | F31: =IF(T2>85,"Eligible","Not Eligible") -> Eligible | I31: =MEDIAN(R2:R6) -> 82 | M31: =_xlfn.STDEV.P(S2:S6) -> 13.181806 | P31: =_xlfn.CONCAT(O2,"-",Answers!P2) -> 1-Rahul | T31: =LEFT(C2,2) -> Am
F32: =IF(T3>85,"Eligible","Not Eligible") -> Eligible | P32: =_xlfn.CONCAT(O3,"-",Answers!P3) -> 2-Sneha | T32: =LEFT(C3,2) -> Ri
F33: =IF(T4>85,"Eligible","Not Eligible") -> Not Eligible | P33: =_xlfn.CONCAT(O4,"-",Answers!P4) -> 3-Arjun | T33: =LEFT(C4,2) -> Ku
F34: =IF(T5>85,"Eligible","Not Eligible") -> Eligible | P34: =_xlfn.CONCAT(O5,"-",Answers!P5) -> 4-Pooja | T34: =LEFT(C5,2) -> Ne
F35: =IF(T6>85,"Eligible","Not Eligible") -> Not Eligible | P35: =_xlfn.CONCAT(O6,"-",Answers!P6) -> 5-Vikas | T35: =LEFT(C6,2) -> Am
A38: Q24 | B38: Final Amount | D38: Q25 | E38: Laptop GT 1 | M38: Q26 | N38: Laptop In North region | Q38: Q27 | R38: Unit Price
B39: 106200 | E39: {=_xlfn._xlws.FILTER(A2:G7,(D2:D7="Laptop")*(E2:E7>1))} -> 301 | F39: North | G39: Amit | H39: Laptop | I39: 2 | J39: 45000 | K39: 45662 | N39: =COUNTIFS(D2:D7,"=Laptop",B2:B7,"=North") -> 1 | R39: =ROUND(F2,-3) -> 45000
B40: 84000 | E40: 306 | F40: South | G40: Riya | H40: Laptop | I40: 2 | J40: 45000 | K40: 18-01-2025 | R40: =ROUND(F3,-3) -> 15000
B41: 60480 | R41: =ROUND(F4,-3) -> 18000
B42: 53100 | R42: =ROUND(F5,-3) -> 45000
B43: 67200 | R43: =ROUND(F6,-3) -> 15000
B44: 106200
